coreason_inference/__init__.py
coreason_inference/analysis/active_scientist.py
coreason_inference/analysis/dynamics.py
coreason_inference/analysis/estimator.py
coreason_inference/analysis/latent.py
coreason_inference/analysis/rule_inductor.py
coreason_inference/analysis/virtual_simulator.py
coreason_inference/engine.py
coreason_inference/schema.py
coreason_inference/server.py
coreason_inference/utils/__init__.py
coreason_inference/utils/logger.py
coreason_inference-0.2.0.dist-info/METADATA
coreason_inference-0.2.0.dist-info/WHEEL
coreason_inference-0.2.0.dist-info/licenses/LICENSE
coreason_inference-0.2.0.dist-info/licenses/NOTICE
coreason_inference-0.2.0.dist-info/RECORD
