Metadata-Version: 2.4
Name: coreason_inference
Version: 0.2.0
Summary: coreason-inference
License: # The Prosperity Public License 3.0.0
License-File: LICENSE
License-File: NOTICE
Author: Gowtham A Rao
Author-email: gowtham.rao@coreason.ai
Requires-Python: >=3.11
Classifier: License :: Other/Proprietary License
Classifier: Programming Language :: Python :: 3.12
Classifier: Operating System :: OS Independent
Requires-Dist: aiofiles (>=23.2.1,<24.0.0)
Requires-Dist: anyio (>=4.0.0,<5.0.0)
Requires-Dist: causal-learn (>=0.1.3,<0.2.0)
Requires-Dist: dowhy (>=0.11,<0.13)
Requires-Dist: econml (>=0.16.0,<0.17.0)
Requires-Dist: fastapi
Requires-Dist: httpx (>=0.27.0,<0.28.0)
Requires-Dist: loguru (>=0.7.2,<0.8.0)
Requires-Dist: networkx (<3.0)
Requires-Dist: numpy (>=1.26.0,<2.0.0)
Requires-Dist: pandas (>=2.3.3,<3.0.0)
Requires-Dist: pydantic (>=2.12.5,<3.0.0)
Requires-Dist: scikit-learn (<1.7)
Requires-Dist: shap (>=0.38.1,<0.49.0)
Requires-Dist: torch (>=2.9.1,<3.0.0)
Requires-Dist: torchdiffeq (>=0.2.5,<0.3.0)
Requires-Dist: uvicorn
Project-URL: Documentation, https://github.com/CoReason-AI/coreason_inference
Project-URL: Homepage, https://github.com/CoReason-AI/coreason_inference
Project-URL: Repository, https://github.com/CoReason-AI/coreason_inference
